lightrag/__init__.py
lightrag/base.py
lightrag/constants.py
lightrag/exceptions.py
lightrag/lightrag.py
lightrag/namespace.py
lightrag/operate.py
lightrag/prompt.py
lightrag/rerank.py
lightrag/types.py
lightrag/utils.py
lightrag/utils_graph.py
lightrag/api/__init__.py
lightrag/api/auth.py
lightrag/api/config.py
lightrag/api/gunicorn_config.py
lightrag/api/lightrag_server.py
lightrag/api/run_with_gunicorn.py
lightrag/api/utils_api.py
lightrag/api/routers/__init__.py
lightrag/api/routers/document_routes.py
lightrag/api/routers/graph_routes.py
lightrag/api/routers/ollama_api.py
lightrag/api/routers/query_routes.py
lightrag/api/static/swagger-ui/favicon-32x32.png
lightrag/api/static/swagger-ui/swagger-ui-bundle.js
lightrag/api/static/swagger-ui/swagger-ui.css
lightrag/api/webui/favicon.png
lightrag/api/webui/index.html
lightrag/api/webui/logo.svg
lightrag/api/webui/assets/KaTeX_AMS-Regular-BQhdFMY1.woff2
lightrag/api/webui/assets/KaTeX_AMS-Regular-DMm9YOAa.woff
lightrag/api/webui/assets/KaTeX_AMS-Regular-DRggAlZN.ttf
lightrag/api/webui/assets/KaTeX_Caligraphic-Bold-ATXxdsX0.ttf
lightrag/api/webui/assets/KaTeX_Caligraphic-Bold-BEiXGLvX.woff
lightrag/api/webui/assets/KaTeX_Caligraphic-Bold-Dq_IR9rO.woff2
lightrag/api/webui/assets/KaTeX_Caligraphic-Regular-CTRA-rTL.woff
lightrag/api/webui/assets/KaTeX_Caligraphic-Regular-Di6jR-x-.woff2
lightrag/api/webui/assets/KaTeX_Caligraphic-Regular-wX97UBjC.ttf
lightrag/api/webui/assets/KaTeX_Fraktur-Bold-BdnERNNW.ttf
lightrag/api/webui/assets/KaTeX_Fraktur-Bold-BsDP51OF.woff
lightrag/api/webui/assets/KaTeX_Fraktur-Bold-CL6g_b3V.woff2
lightrag/api/webui/assets/KaTeX_Fraktur-Regular-CB_wures.ttf
lightrag/api/webui/assets/KaTeX_Fraktur-Regular-CTYiF6lA.woff2
lightrag/api/webui/assets/KaTeX_Fraktur-Regular-Dxdc4cR9.woff
lightrag/api/webui/assets/KaTeX_Main-Bold-Cx986IdX.woff2
lightrag/api/webui/assets/KaTeX_Main-Bold-Jm3AIy58.woff
lightrag/api/webui/assets/KaTeX_Main-Bold-waoOVXN0.ttf
lightrag_hku-1.4.9.10.dist-info/licenses/LICENSE
lightrag_hku-1.4.9.10.dist-info/METADATA
lightrag_hku-1.4.9.10.dist-info/WHEEL
lightrag_hku-1.4.9.10.dist-info/entry_points.txt
lightrag_hku-1.4.9.10.dist-info/top_level.txt
lightrag_hku-1.4.9.10.dist-info/RECORD
